semhash/__init__.py
semhash/datamodels.py
semhash/index.py
semhash/records.py
semhash/semhash.py
semhash/utils.py
semhash/version.py
semhash-0.4.1.dist-info/METADATA
semhash-0.4.1.dist-info/WHEEL
semhash-0.4.1.dist-info/top_level.txt
semhash-0.4.1.dist-info/RECORD
