Metadata-Version: 2.4
Name: semhash
Version: 0.4.1
Summary: Fast Multimodal Semantic Deduplication & Filtering
Author-email: Thomas van Dongen <thomas123@live.nl>, Stéphan Tulkens <stephantul@gmail.com>
License: MIT License
Project-URL: Homepage, https://github.com/MinishLab
Project-URL: Bug Reports, https://github.com/MinishLab/semhash/issues
Project-URL: Source, https://github.com/MinishLab/semhash
Classifier: Development Status :: 4 - Beta
Classifier: Intended Audience :: Developers
Classifier: Intended Audience :: Science/Research
Classifier: Topic :: Scientific/Engineering :: Artificial Intelligence
Classifier: Topic :: Software Development :: Libraries
Classifier: License :: OSI Approved :: MIT License
Classifier: Programming Language :: Python :: 3 :: Only
Classifier: Programming Language :: Python :: 3.10
Classifier: Programming Language :: Python :: 3.11
Classifier: Programming Language :: Python :: 3.12
Classifier: Natural Language :: English
Requires-Python: >=3.10
Requires-Dist: model2vec>=0.3.4
Requires-Dist: vicinity[usearch]>=0.4.3
Requires-Dist: frozendict
Requires-Dist: pyversity
Provides-Extra: dev
Requires-Dist: black; extra == "dev"
Requires-Dist: ipython; extra == "dev"
Requires-Dist: mypy; extra == "dev"
Requires-Dist: pre-commit; extra == "dev"
Requires-Dist: pytest; extra == "dev"
Requires-Dist: pytest-coverage; extra == "dev"
Requires-Dist: ruff; extra == "dev"
